Metadata-Version: 2.1
Name: statuspagePy
Version: 1.0.0
Summary: A Python implementation of the Atlassian Statuspage API, offering an intuitive and efficient approach to managing and controlling Atlassian Statuspage services.
Home-page: https://github.com/dielect/PyStatusPage
Author: dielectric
Author-email: dielectric.army@gmail.com
Classifier: Programming Language :: Python :: 3
Classifier: License :: OSI Approved :: MIT License
Classifier: Operating System :: OS Independent
Requires-Python: >=3.6
License-File: LICENSE
Requires-Dist: requests (~=2.28.2)
